LICENSE
flask_restx_marshmallow/__init__.py
flask_restx_marshmallow/_json.py
flask_restx_marshmallow/api.py
flask_restx_marshmallow/enum.py
flask_restx_marshmallow/namespace.py
flask_restx_marshmallow/parameter.py
flask_restx_marshmallow/schema.py
flask_restx_marshmallow/static/swagger-ui-bundle.min.js
flask_restx_marshmallow/static/swagger-ui-standalone-preset.min.js
flask_restx_marshmallow/static/swagger-ui.min.css
flask_restx_marshmallow/static/swagger_fav.png
flask_restx_marshmallow/swagger.py
flask_restx_marshmallow/templates/index.html.j2
flask_restx_marshmallow/templates/local.html.j2
flask_restx_marshmallow/type.py
flask_restx_marshmallow/util.py
flask_restx_marshmallow-0.2.0.dist-info/LICENSE
flask_restx_marshmallow-0.2.0.dist-info/METADATA
flask_restx_marshmallow-0.2.0.dist-info/WHEEL
flask_restx_marshmallow-0.2.0.dist-info/RECORD
