Metadata-Version: 2.1
Name: flask_restx_marshmallow
Version: 0.2.0
Summary: A successful practice combining flask_restx with marshmallow
Home-page: https://1746104160.github.io/flask-restx-marshmallow/
License: MIT
Keywords: flask,flask_restx,sqlalchemy,marshmallow
Author: 1746104160
Author-email: shaojiahong2001@outlook.com
Requires-Python: >=3.12,<4.0
Classifier: Intended Audience :: Developers
Classifier: License :: OSI Approved :: MIT License
Classifier: Programming Language :: Python
Classifier: Programming Language :: Python :: 3
Classifier: Programming Language :: Python :: 3.12
Classifier: Programming Language :: Python :: 3 :: Only
Classifier: Programming Language :: Python :: 3.13
Classifier: Topic :: Software Development
Classifier: Topic :: Software Development :: Libraries
Requires-Dist: apispec (>=6.8.2,<7.0.0)
Requires-Dist: docstring-parser (>=0.16,<0.17)
Requires-Dist: flask-restx (>=1.3.0,<2.0.0)
Requires-Dist: marshmallow-dataclass (>=8.7.1,<9.0.0)
Requires-Dist: requests (>=2.32.4,<3.0.0)
Requires-Dist: webargs (>=8.7.0,<9.0.0)
Project-URL: Repository, https://github.com/1746104160/flask-restx-marshmallow
